[{"__symbolic":"module","version":3,"metadata":{"isPresent":{"__symbolic":"function","parameters":["obj"],"value":{"__symbolic":"binop","operator":"&&","left":{"__symbolic":"binop","operator":"!==","left":{"__symbolic":"reference","name":"obj"},"right":{"__symbolic":"reference","name":"undefined"}},"right":{"__symbolic":"binop","operator":"!==","left":{"__symbolic":"reference","name":"obj"},"right":null}}}}},{"__symbolic":"module","version":1,"metadata":{"isPresent":{"__symbolic":"function","parameters":["obj"],"value":{"__symbolic":"binop","operator":"&&","left":{"__symbolic":"binop","operator":"!==","left":{"__symbolic":"reference","name":"obj"},"right":{"__symbolic":"reference","name":"undefined"}},"right":{"__symbolic":"binop","operator":"!==","left":{"__symbolic":"reference","name":"obj"},"right":null}}}}}]